[{"text": "my father used to give my brother and I", "start": 0.0, "duration": 3.659}, {"text": "food my sisters didn't have to eat", "start": 1.77, "duration": 4.89}, {"text": "he called it man food it was sardines in", "start": 3.659, "duration": 5.12}, {"text": "a can", "start": 6.66, "duration": 2.119}, {"text": "he said I might eat this he said it'll", "start": 8.78, "duration": 6.279}, {"text": "put hair on your chest I'm 8 years old", "start": 11.519, "duration": 9.451}, {"text": "and a good thing he said every man wants", "start": 15.059, "duration": 9.001}, {"text": "hair on his chest boy really yeah who", "start": 20.97, "duration": 4.71}, {"text": "knew in the 21st century all the men", "start": 24.06, "duration": 3.24}, {"text": "would be wax and all the hair off their", "start": 25.68, "duration": 6.75}, {"text": "child I want to meet the first man that", "start": 27.3, "duration": 6.84}, {"text": "ripped the hair out of his chest I", "start": 32.43, "duration": 3.12}, {"text": "really do cuz I'm gonna punch him right", "start": 34.14, "duration": 3.079}, {"text": "in the face", "start": 35.55, "duration": 5.689}, {"text": "in a Christian loving way", "start": 37.219, "duration": 4.02}, {"text": "Tammy says to me about a year ago she", "start": 46.06, "duration": 3.76}, {"text": "goes I want you to look into the waxing", "start": 48.35, "duration": 2.55}, {"text": "thing that's what she said sir how much", "start": 49.82, "duration": 2.6}, {"text": "should look into the waxing thing I", "start": 50.9, "duration": 4.05}, {"text": "honored my wife I looked into the waxing", "start": 52.42, "duration": 5.139}, {"text": "thing came back and told her get used to", "start": 54.95, "duration": 7.17}, {"text": "the pelt it's not going anywhere are you", "start": 57.559, "duration": 6.241}, {"text": "kidding me if we lost our minds as a", "start": 62.12, "duration": 4.68}, {"text": "culture we spent billions of dollars to", "start": 63.8, "duration": 4.47}, {"text": "have somebody ripped the hair out of our", "start": 66.8, "duration": 5.85}, {"text": "body by the root that hurts but we won't", "start": 68.27, "duration": 6.72}, {"text": "let our federal government drip water on", "start": 72.65, "duration": 5.69}, {"text": "the faces of terrorists", "start": 74.99, "duration": 3.35}, {"text": "[Applause]", "start": 81.28, "duration": 6.53}, {"text": "I think the CIA B's to open up some", "start": 84.03, "duration": 6.92}, {"text": "spies around the world", "start": 87.81, "duration": 3.14}, {"text": "you know Achmed before we send you back", "start": 95.5, "duration": 3.75}, {"text": "to the battlefield as part of the new", "start": 97.66, "duration": 3.51}, {"text": "Western civilization catch and release", "start": 99.25, "duration": 6.03}, {"text": "program you're in luck the US", "start": 101.17, "duration": 6.03}, {"text": "government's gonna clean you up today my", "start": 105.28, "duration": 2.6}, {"text": "man", "start": 107.2, "duration": 3.63}, {"text": "both 72 maidens you're dying to lay with", "start": 107.88, "duration": 5.38}, {"text": "in the next life they don't wanna lay", "start": 110.83, "duration": 8.07}, {"text": "next to a throw rug so get into van my", "start": 113.26, "duration": 7.32}, {"text": "hearse to a little friend we're going to", "start": 118.9, "duration": 4.01}, {"text": "the ball", "start": 120.58, "duration": 2.33}, {"text": "it's just a thought", "start": 128.41, "duration": 3.569}, {"text": "so full disclosure I got waxed", "start": 133.99, "duration": 4.85}, {"text": "[Music]", "start": 140.72, "duration": 3.68}, {"text": "tami kept pushing it pushing it pushes", "start": 142.06, "duration": 4.32}, {"text": "she finally said the magic words she", "start": 144.4, "duration": 5.18}, {"text": "said I think it would be sexy on you", "start": 146.38, "duration": 5.61}, {"text": "look at my wife and I've been married 33", "start": 149.58, "duration": 5.35}, {"text": "years sexy is not a word often used in", "start": 151.99, "duration": 6.9}, {"text": "our our idea of sexting is we send", "start": 154.93, "duration": 5.61}, {"text": "pictures of desserts to each other on", "start": 158.89, "duration": 5.099}, {"text": "our cellphones I'll get it back from her", "start": 160.54, "duration": 7.01}, {"text": "then a six layered carrot cake", "start": 163.989, "duration": 3.561}, {"text": "so I don't care what it is if my wife", "start": 172.989, "duration": 4.51}, {"text": "said to me your face tattoo would be", "start": 175.76, "duration": 3.569}, {"text": "sexy I'm getting it done that's all I'm", "start": 177.499, "duration": 2.571}, {"text": "saying", "start": 179.329, "duration": 1.481}, {"text": "[Applause]", "start": 180.07, "duration": 3.059}, {"text": "[Music]", "start": 180.81, "duration": 4.849}, {"text": "there are three billion women that", "start": 183.129, "duration": 5.17}, {"text": "inhabit planet Earth I only care if one", "start": 185.659, "duration": 4.86}, {"text": "of those women thinks I'm sexy that's it", "start": 188.299, "duration": 6.39}, {"text": "huh so I made a decision when she leaves", "start": 190.519, "duration": 6.0}, {"text": "town I was gonna surprise her I said I'm", "start": 194.689, "duration": 5.73}, {"text": "gonna get way I got onto Google I looked", "start": 196.519, "duration": 8.911}, {"text": "up the waxy people found me gel its meat", "start": 200.419, "duration": 6.66}, {"text": "gel don't make the mistake of calling", "start": 205.43, "duration": 4.52}, {"text": "her Michel", "start": 207.079, "duration": 2.871}, {"text": "apparently I hit a sore spot so meat gel", "start": 212.68, "duration": 8.08}, {"text": "gets me all ready to go well have enough", "start": 217.73, "duration": 4.679}, {"text": "got a piece of tape there she says", "start": 220.76, "duration": 4.83}, {"text": "you're ready I said yeah you know she", "start": 222.409, "duration": 9.931}, {"text": "goes I've never had that happen I tried", "start": 225.59, "duration": 10.009}, {"text": "to scream and nothing came out", "start": 232.34, "duration": 3.259}, {"text": "I got a finger there were dogs two", "start": 236.319, "duration": 4.7}, {"text": "blocks away gun", "start": 238.12, "duration": 2.899}, {"text": "sounds like another man's getting a wax", "start": 244.15, "duration": 2.46}, {"text": "job", "start": 246.01, "duration": 2.089}, {"text": "[Music]", "start": 246.61, "duration": 4.749}, {"text": "with me child", "start": 248.099, "duration": 3.26}, {"text": "and are so bad I'm telling him I and she", "start": 253.31, "duration": 5.19}, {"text": "starts to put another piece of tape on", "start": 256.88, "duration": 4.62}, {"text": "me and I can't get up tamping out like a", "start": 258.5, "duration": 8.85}, {"text": "restaurant let me find my voice I said", "start": 261.5, "duration": 11.1}, {"text": "no get away from me you sick woman don't", "start": 267.35, "duration": 7.88}, {"text": "touch me", "start": 272.6, "duration": 2.63}, {"text": "[Music]", "start": 278.51, "duration": 4.059}, {"text": "that's what I wanted to say when I", "start": 281.069, "duration": 6.6}, {"text": "couldn't say I was gonna quit I really", "start": 282.569, "duration": 6.63}, {"text": "was I was gonna leave and I looked in", "start": 287.669, "duration": 3.53}, {"text": "the mirror and I had this weights trim", "start": 289.199, "duration": 4.291}, {"text": "and looking at your name tag with no", "start": 291.199, "duration": 5.981}, {"text": "name on it it was just and all these", "start": 293.49, "duration": 7.799}, {"text": "weeds around it so you're locked in I", "start": 297.18, "duration": 6.209}, {"text": "couldn't stop anyways just says I can", "start": 301.289, "duration": 3.63}, {"text": "take my time I go don't take it just get", "start": 303.389, "duration": 11.31}, {"text": "it over with just cleans me up I look in", "start": 304.919, "duration": 11.46}, {"text": "the mirror I was thinking sir I was", "start": 314.699, "duration": 4.381}, {"text": "peeing it was raw pee I looked like a", "start": 316.379, "duration": 6.53}, {"text": "flabby piece of brazuca bubblegum", "start": 319.08, "duration": 3.829}, {"text": "and all I can think of as she fakes it", "start": 325.75, "duration": 6.69}, {"text": "sexy okay well coming for taste but I'm", "start": 327.55, "duration": 8.22}, {"text": "all-in so the next day she came home", "start": 332.44, "duration": 4.68}, {"text": "from the road and I went on a surprise", "start": 335.77, "duration": 2.61}, {"text": "her so I went in the bathroom put on", "start": 337.12, "duration": 2.97}, {"text": "some shorts I took off my shirt standing", "start": 338.38, "duration": 3.3}, {"text": "there shorts no shirt trying to get her", "start": 340.09, "duration": 3.69}, {"text": "to notice while we're a converse thing", "start": 341.68, "duration": 5.0}, {"text": "[Music]", "start": 343.78, "duration": 5.07}, {"text": "she looks at me she says are you having", "start": 346.68, "duration": 9.55}, {"text": "a stroke no she goes what'd you do I", "start": 348.85, "duration": 14.819}, {"text": "said I got waxed that's a reaction I was", "start": 356.23, "duration": 11.1}, {"text": "looking for what Zeus she goes Oh put a", "start": 363.669, "duration": 6.571}, {"text": "shirt on is creeping me out she goes you", "start": 367.33, "duration": 6.56}, {"text": "look like Patrick from SpongeBob", "start": 370.24, "duration": 3.65}, {"text": "the things you do to honor your wife sir", "start": 382.949, "duration": 8.2}, {"text": "[Music]", "start": 385.73, "duration": 5.419}, {"text": "hey everybody did you know that drive", "start": 391.27, "duration": 4.8}, {"text": "our comedy had their own app everybody", "start": 393.13, "duration": 5.7}, {"text": "has an app but not like this one you can", "start": 396.07, "duration": 4.56}, {"text": "get it right now on your phone and watch", "start": 398.83, "duration": 6.35}, {"text": "my entire special how cool is that", "start": 400.63, "duration": 4.55}]